polars_upgrade/__init__.py
polars_upgrade/__main__.py
polars_upgrade/_ast_helpers.py
polars_upgrade/_data.py
polars_upgrade/_main.py
polars_upgrade/_string_helpers.py
polars_upgrade/_token_helpers.py
polars_upgrade/_plugins/enable_string_cache.py
polars_upgrade/_plugins/group_by_dynamic_truncate.py
polars_upgrade/_plugins/map_dict.py
polars_upgrade/_plugins/map_groups.py
polars_upgrade/_plugins/outer_coalesce.py
polars_upgrade/_plugins/pivot_kwonly.py
polars_upgrade/_plugins/removed_expr_arguments.py
polars_upgrade/_plugins/renamed_dataframe_method_arguments.py
polars_upgrade/_plugins/renamed_dataframe_method_values.py
polars_upgrade/_plugins/renamed_dataframe_methods.py
polars_upgrade/_plugins/renamed_datetime_functions.py
polars_upgrade/_plugins/renamed_expr_arguments.py
polars_upgrade/_plugins/renamed_expr_functions.py
polars_upgrade/_plugins/renamed_list_arguments.py
polars_upgrade/_plugins/renamed_list_functions.py
polars_upgrade/_plugins/renamed_meta_functions.py
polars_upgrade/_plugins/renamed_str_arguments.py
polars_upgrade/_plugins/renamed_string_functions.py
polars_upgrade/_plugins/renamed_toplevel_arguments.py
polars_upgrade/_plugins/renamed_toplevel_functions.py
polars_upgrade/_plugins/renamed_toplevel_no_arg_functions.py
polars_upgrade/_plugins/rolling_agg_by.py
polars_upgrade/_plugins/saturating.py
polars_upgrade/_plugins/with_row_count.py
polars_upgrade-0.3.6.dist-info/METADATA
polars_upgrade-0.3.6.dist-info/WHEEL
polars_upgrade-0.3.6.dist-info/entry_points.txt
polars_upgrade-0.3.6.dist-info/licenses/LICENSE
polars_upgrade-0.3.6.dist-info/RECORD
