Metadata-Version: 2.3
Name: polars_upgrade
Version: 0.3.6
Summary: Automatically upgrade Polars code to the latest version.
Author-email: Marco Gorelli <33491632+MarcoGorelli@users.noreply.github.com>
License-File: LICENSE
Classifier: License :: OSI Approved :: MIT License
Classifier: Operating System :: OS Independent
Classifier: Programming Language :: Python :: 3
Requires-Python: >=3.9
Requires-Dist: tokenize-rt>=5.2.0
